senoquant/__init__.py
senoquant/_reader.py
senoquant/_widget.py
senoquant/napari.yaml
senoquant/utils.py
senoquant/reader/__init__.py
senoquant/reader/core.py
senoquant/tabs/__init__.py
senoquant/tabs/batch/__init__.py
senoquant/tabs/batch/backend.py
senoquant/tabs/batch/config.py
senoquant/tabs/batch/frontend.py
senoquant/tabs/batch/io.py
senoquant/tabs/batch/layers.py
senoquant/tabs/quantification/__init__.py
senoquant/tabs/quantification/backend.py
senoquant/tabs/quantification/frontend.py
senoquant/tabs/quantification/features/__init__.py
senoquant/tabs/quantification/features/base.py
senoquant/tabs/quantification/features/roi.py
senoquant/tabs/quantification/features/marker/__init__.py
senoquant/tabs/quantification/features/marker/config.py
senoquant/tabs/quantification/features/marker/dialog.py
senoquant/tabs/quantification/features/marker/export.py
senoquant/tabs/quantification/features/marker/feature.py
senoquant/tabs/quantification/features/marker/morphology.py
senoquant/tabs/quantification/features/marker/rows.py
senoquant/tabs/quantification/features/marker/thresholding.py
senoquant/tabs/quantification/features/spots/__init__.py
senoquant/tabs/quantification/features/spots/config.py
senoquant/tabs/quantification/features/spots/dialog.py
senoquant/tabs/quantification/features/spots/export.py
senoquant/tabs/quantification/features/spots/feature.py
senoquant/tabs/quantification/features/spots/morphology.py
senoquant/tabs/quantification/features/spots/rows.py
senoquant/tabs/segmentation/__init__.py
senoquant/tabs/segmentation/backend.py
senoquant/tabs/segmentation/frontend.py
senoquant/tabs/segmentation/models/__init__.py
senoquant/tabs/segmentation/models/base.py
senoquant/tabs/segmentation/models/hf.py
senoquant/tabs/segmentation/models/cpsam/details.json
senoquant/tabs/segmentation/models/cpsam/model.py
senoquant/tabs/segmentation/models/default_2d/details.json
senoquant/tabs/segmentation/models/default_2d/model.py
senoquant-1.0.0b2.dist-info/licenses/LICENSE
senoquant-1.0.0b2.dist-info/METADATA
senoquant-1.0.0b2.dist-info/WHEEL
senoquant-1.0.0b2.dist-info/entry_points.txt
senoquant-1.0.0b2.dist-info/top_level.txt
senoquant-1.0.0b2.dist-info/RECORD
