Metadata-Version: 2.4
Name: senoquant
Version: 1.0.0b2
Summary: Napari plugin for spatial quantification of senescence markers in tissue imaging
Author: SenoQuant Contributors
Maintainer: SenoQuant Contributors
License: BSD-3-Clause
Project-URL: Homepage, https://github.com/HaamsRee/senoquant-dev
Project-URL: Documentation, https://haamsree.github.io/senoquant-dev/
Project-URL: Repository, https://github.com/HaamsRee/senoquant-dev
Project-URL: Bug Tracker, https://github.com/HaamsRee/senoquant-dev/issues
Keywords: napari,plugin,senescence,quantification,microscopy,image analysis,segmentation,spot detection
Classifier: Development Status :: 4 - Beta
Classifier: Framework :: napari
Classifier: Intended Audience :: Science/Research
Classifier: License :: OSI Approved :: BSD License
Classifier: Operating System :: OS Independent
Classifier: Programming Language :: Python :: 3
Classifier: Programming Language :: Python :: 3.11
Classifier: Programming Language :: Python :: 3.12
Classifier: Topic :: Scientific/Engineering :: Bio-Informatics
Classifier: Topic :: Scientific/Engineering :: Image Processing
Requires-Python: >=3.11
License-File: LICENSE
Requires-Dist: bioio>=3.2.0
Requires-Dist: bioio-czi>=2.4.2
Requires-Dist: bioio-dv>=1.2.0
Requires-Dist: bioio-imageio>=1.3.0
Requires-Dist: bioio-lif>=1.4.0
Requires-Dist: bioio-nd2>=1.6.0
Requires-Dist: bioio-ome-tiff>=1.4.0
Requires-Dist: bioio-ome-zarr>=3.2.1
Requires-Dist: bioio-sldy>=1.4.0
Requires-Dist: bioio-tifffile>=1.3.0
Requires-Dist: bioio-tiff-glob>=1.2.0
Requires-Dist: numpy<=1.26.4,>=1.23
Requires-Dist: cellpose==4.0.8
Requires-Dist: onnx>=1.16
Requires-Dist: onnxruntime>=1.16; platform_system == "Darwin"
Requires-Dist: onnxruntime-gpu>=1.16; platform_system != "Darwin"
Requires-Dist: openpyxl>=3.1
Requires-Dist: huggingface_hub>=0.23.0
Requires-Dist: scikit-image<0.25,>=0.22
Requires-Dist: scipy>=1.8
Requires-Dist: senoquant-stardist-ext>=0.1.0
Requires-Dist: dask[array]>=2024.4
Requires-Dist: dask[distributed]>=2024.4
Provides-Extra: gpu
Requires-Dist: cupy-cuda12x>=12.0; extra == "gpu"
Requires-Dist: cucim>=23.4; extra == "gpu"
Provides-Extra: all
Requires-Dist: napari[all]; extra == "all"
Requires-Dist: bioio>=3.2.0; extra == "all"
Requires-Dist: bioio-czi>=2.4.2; extra == "all"
Requires-Dist: bioio-dv>=1.2.0; extra == "all"
Requires-Dist: bioio-imageio>=1.3.0; extra == "all"
Requires-Dist: bioio-lif>=1.4.0; extra == "all"
Requires-Dist: bioio-nd2>=1.6.0; extra == "all"
Requires-Dist: bioio-ome-tiff>=1.4.0; extra == "all"
Requires-Dist: bioio-ome-zarr>=3.2.1; extra == "all"
Requires-Dist: bioio-sldy>=1.4.0; extra == "all"
Requires-Dist: bioio-tifffile>=1.3.0; extra == "all"
Requires-Dist: bioio-tiff-glob>=1.2.0; extra == "all"
Requires-Dist: numpy<=1.26.4,>=1.23; extra == "all"
Requires-Dist: cellpose==4.0.8; extra == "all"
Requires-Dist: onnx>=1.16; extra == "all"
Requires-Dist: onnxruntime>=1.16; platform_system == "Darwin" and extra == "all"
Requires-Dist: onnxruntime-gpu>=1.16; platform_system != "Darwin" and extra == "all"
Requires-Dist: openpyxl>=3.1; extra == "all"
Requires-Dist: huggingface_hub>=0.23.0; extra == "all"
Requires-Dist: scikit-image<0.25,>=0.22; extra == "all"
Requires-Dist: scipy>=1.8; extra == "all"
Requires-Dist: senoquant-stardist-ext>=0.1.0; extra == "all"
Requires-Dist: dask[array]>=2024.4; extra == "all"
Requires-Dist: dask[distributed]>=2024.4; extra == "all"
Requires-Dist: cupy-cuda12x>=12.0; extra == "all"
Requires-Dist: cucim>=23.4; extra == "all"
Dynamic: license-file
